{
  "project_info": {
    "project_number": "138882873861",
    "firebase_url": "https://pushnoti34-default-rtdb.firebaseio.com",
    "project_id": "pushnoti34",
    "storage_bucket": "pushnoti34.appspot.com"
  },
  "client": [
    {
      "client_info": {
        "mobilesdk_app_id": "1:138882873861:android:447f7cb0b87f5befc57a6c",
        "android_client_info": {
          "package_name": "com.shadow.blackhole"
        }
      },
      "oauth_client": [
        {
          "client_id": "138882873861-gc3iuf3dvu0g225u2aa2a8lm0pe0po66.apps.googleusercontent.com",
          "client_type": 3
        }
      ],
      "api_key": [
        {
          "current_key": "AIzaSyAjCdMWvB_MDcDENPVnnQEDZNnicKJemHg"
        }
      ],
      "services": {
        "appinvite_service": {
          "other_platform_oauth_client": [
            {
              "client_id": "138882873861-gc3iuf3dvu0g225u2aa2a8lm0pe0po66.apps.googleusercontent.com",
              "client_type": 3
            }
          ]
        }
      }
    }
  ],
  "configuration_version": "1"
}